sliceup/__init__.py
sliceup/functions.py
sliceup/sliceup.py
sliceup-0.2.0.dist-info/LICENSE
sliceup-0.2.0.dist-info/METADATA
sliceup-0.2.0.dist-info/WHEEL
sliceup-0.2.0.dist-info/top_level.txt
sliceup-0.2.0.dist-info/RECORD
