Metadata-Version: 2.1
Name: sliceup
Version: 0.2.0
Summary: Python client for SliceUp
Home-page: https://github.com/sliceup/sliceup-python
Author: SliceUp, Inc
Author-email: info@sliceup.com
License: UNKNOWN
Platform: UNKNOWN
Classifier: Programming Language :: Python :: 3
Classifier: License :: OSI Approved :: MIT License
Classifier: Operating System :: OS Independent
Requires-Python: >=3.6
